waldur_site_agent_rancher/__init__.py
waldur_site_agent_rancher/backend.py
waldur_site_agent_rancher/keycloak_client.py
waldur_site_agent_rancher/rancher_client.py
waldur_site_agent_rancher-0.8.2.dist-info/METADATA
waldur_site_agent_rancher-0.8.2.dist-info/WHEEL
waldur_site_agent_rancher-0.8.2.dist-info/entry_points.txt
waldur_site_agent_rancher-0.8.2.dist-info/RECORD
