Metadata-Version: 2.4
Name: waldur-site-agent-rancher
Version: 0.8.2
Summary: Rancher plugin for Waldur Site Agent
Author-email: OpenNode Team <info@opennodecloud.com>
Requires-Python: <4,>=3.9
Requires-Dist: python-keycloak>=3.0.0
Requires-Dist: requests>=2.31.0
Requires-Dist: waldur-site-agent>=0.7.0
